carculator/__init__.py
carculator/car_input_parameters.py
carculator/inventory.py
carculator/model.py
carculator/data/default_parameters.json
carculator/data/extra_parameters.json
carculator/data/purchase_cost_params.yaml
carculator-1.9.4.dist-info/licenses/LICENSE
carculator-1.9.4.dist-info/METADATA
carculator-1.9.4.dist-info/WHEEL
carculator-1.9.4.dist-info/top_level.txt
carculator-1.9.4.dist-info/RECORD
